.bumpversion.cfg
.readthedocs.yml
CONTRIBUTING.md
LICENSE
MANIFEST.in
Makefile
README.md
pyproject.toml
setup.py
docs/Makefile
docs/conf.py
docs/index.md
docs/make.bat
docs/requirements.txt
docs/images/cli_recording.gif
docs/images/demo_recording.gif
docs/images/screenshot.png
docs/source/easierscrape.rst
docs/source/modules.rst
easierscrape/__init__.py
easierscrape/__main__.py
easierscrape/_version.py
easierscrape/easierscrape.py
easierscrape.egg-info/PKG-INFO
easierscrape.egg-info/SOURCES.txt
easierscrape.egg-info/dependency_links.txt
easierscrape.egg-info/requires.txt
easierscrape.egg-info/top_level.txt
easierscrape/tests/test_all.py