Metadata-Version: 2.1
Name: easierscrape
Version: 0.2.2
Summary: A library which does some basic web scraping operations
Author-email: Daniel Greco <dag2226@columbia.edu>
License:                                  Apache License
Project-URL: repository, https://github.com/dag2226/easierscrape
Classifier: Development Status :: 2 - Pre-Alpha
Classifier: Programming Language :: Python :: Implementation :: CPython
Classifier: Programming Language :: Python :: Implementation :: PyPy
Classifier: Programming Language :: Python :: 3
Classifier: Programming Language :: Python :: 3.7
Classifier: Programming Language :: Python :: 3.8
Classifier: Programming Language :: Python :: 3.9
Classifier: Programming Language :: Python :: 3.10
Classifier: Programming Language :: Python :: 3.11
Requires-Python: >=3.7
Provides-Extra: develop
License-File: LICENSE
